setup.py
pyutd/__init__.py
pyutd/test.py
pyutd.egg-info/PKG-INFO
pyutd.egg-info/SOURCES.txt
pyutd.egg-info/dependency_links.txt
pyutd.egg-info/not-zip-safe
pyutd.egg-info/top_level.txt