Metadata-Version: 1.0
Name: pyutd
Version: 0.1
Summary: python package for Modern Uniform Theory of diffraction
Home-page: https://github.com/bazingaedward/pyUTD
Author: Edward Qiu
Author-email: bazingaedward@gmail.com
License: MIT
Platform: UNKNOWN
